odoo/addons/helpdesk_mgmt_project/README.rst
odoo/addons/helpdesk_mgmt_project/__init__.py
odoo/addons/helpdesk_mgmt_project/__manifest__.py
odoo/addons/helpdesk_mgmt_project/i18n/es.po
odoo/addons/helpdesk_mgmt_project/i18n/es_AR.po
odoo/addons/helpdesk_mgmt_project/i18n/fr.po
odoo/addons/helpdesk_mgmt_project/i18n/helpdesk_mgmt_project.pot
odoo/addons/helpdesk_mgmt_project/i18n/it.po
odoo/addons/helpdesk_mgmt_project/i18n/pt.po
odoo/addons/helpdesk_mgmt_project/models/__init__.py
odoo/addons/helpdesk_mgmt_project/models/helpdesk_ticket.py
odoo/addons/helpdesk_mgmt_project/models/project.py
odoo/addons/helpdesk_mgmt_project/models/project_task.py
odoo/addons/helpdesk_mgmt_project/readme/CONTRIBUTORS.rst
odoo/addons/helpdesk_mgmt_project/readme/DESCRIPTION.rst
odoo/addons/helpdesk_mgmt_project/static/description/icon.png
odoo/addons/helpdesk_mgmt_project/static/description/index.html
odoo/addons/helpdesk_mgmt_project/tests/__init__.py
odoo/addons/helpdesk_mgmt_project/tests/test_helpdesk_ticket.py
odoo/addons/helpdesk_mgmt_project/views/helpdesk_ticket_view.xml
odoo/addons/helpdesk_mgmt_project/views/project_task_view.xml
odoo/addons/helpdesk_mgmt_project/views/project_view.xml
odoo13_addon_helpdesk_mgmt_project-13.0.1.0.1.dist-info/METADATA
odoo13_addon_helpdesk_mgmt_project-13.0.1.0.1.dist-info/WHEEL
odoo13_addon_helpdesk_mgmt_project-13.0.1.0.1.dist-info/top_level.txt
odoo13_addon_helpdesk_mgmt_project-13.0.1.0.1.dist-info/RECORD
